{
   "LKO-LucknowDEL-Delhi2020-01-05": {
      "flight": [
         {
            "depart_time": "09:45",
            "travel_time": "4h 45m",
            "stops": "1",
            "flight": "Air India",
            "price": 9813,
            "arrival_time": "11:15",
            "coupon": {
               "paytm": [
                  "FLYPTM",
                  "FIRSTFLIGHT",
                  "FIRSTINTLTRIP",
                  "FLY2",
                  "FLY3",
                  "FLY4"
               ],
               "mmt": [
                  "MMTFLIGHT",
                  "MMTNEWFLY",
                  "FLYNOW",
                  "MMTFYLMON",
                  "HSBCDOM",
                  "FLYMON",
                  "RBLMMT",
                  "MMTIDFC"
               ],
               "goibigo": [
                  "FLYNEW",
                  "FLYINT",
                  "WINTER",
                  "MYSTERYDEAL",
                  "GOPAYPAL"
               ],
               "yatra": [
                  "FLASH2020",
                  "FREEFLY",
                  "YTINTFLY",
                  "YATRANEW",
                  "STCEMI",
                  "AXISEMI19",
                  "NEWPAY",
                  "DIGISMART"
               ],
               "happyeasygo": [
                  "HEGNEW",
                  "HEGOLAN",
                  "HEGOLAA",
                  "HEGDMF",
                  "HEGINF",
                  "HEGARTL",
                  "HEGART1",
                  "HEGAPP",
                  "HEG360",
                  "HEGPAL"
               ]
            }
         },
         {
            "depart_time": "09:45",
            "travel_time": "22h 30m",
            "stops": "1",
            "flight": "Air India",
            "price": 9971,
            "arrival_time": "11:15",
            "coupon": {
               "paytm": [
                  "FLYPTM",
                  "FIRSTFLIGHT",
                  "FIRSTINTLTRIP",
                  "FLY2",
                  "FLY3",
                  "FLY4"
               ],
               "mmt": [
                  "MMTFLIGHT",
                  "MMTNEWFLY",
                  "FLYNOW",
                  "MMTFYLMON",
                  "HSBCDOM",
                  "FLYMON",
                  "RBLMMT",
                  "MMTIDFC"
               ],
               "goibigo": [
                  "FLYNEW",
                  "FLYINT",
                  "WINTER",
                  "MYSTERYDEAL",
                  "GOPAYPAL"
               ],
               "yatra": [
                  "FLASH2020",
                  "FREEFLY",
                  "YTINTFLY",
                  "YATRANEW",
                  "STCEMI",
                  "AXISEMI19",
                  "NEWPAY",
                  "DIGISMART"
               ],
               "happyeasygo": [
                  "HEGNEW",
                  "HEGOLAN",
                  "HEGOLAA",
                  "HEGDMF",
                  "HEGINF",
                  "HEGARTL",
                  "HEGART1",
                  "HEGAPP",
                  "HEG360",
                  "HEGPAL"
               ]
            }
         },
         {
            "depart_time": "14:05",
            "travel_time": "1h 20m",
            "stops": "0",
            "flight": "Air India",
            "price": 13089,
            "arrival_time": "15:25",
            "coupon": {
               "paytm": [
                  "FLYPTM",
                  "FIRSTFLIGHT",
                  "FIRSTINTLTRIP",
                  "FLY2",
                  "FLY3",
                  "FLY4"
               ],
               "mmt": [
                  "MMTFLIGHT",
                  "MMTNEWFLY",
                  "FLYNOW",
                  "MMTFYLMON",
                  "HSBCDOM",
                  "FLYMON",
                  "RBLMMT",
                  "MMTIDFC"
               ],
               "goibigo": [
                  "FLYNEW",
                  "FLYINT",
                  "WINTER",
                  "MYSTERYDEAL",
                  "GOPAYPAL"
               ],
               "yatra": [
                  "FLASH2020",
                  "FREEFLY",
                  "YTINTFLY",
                  "YATRANEW",
                  "STCEMI",
                  "AXISEMI19",
                  "NEWPAY",
                  "DIGISMART"
               ],
               "happyeasygo": [
                  "HEGNEW",
                  "HEGOLAN",
                  "HEGOLAA",
                  "HEGDMF",
                  "HEGINF",
                  "HEGARTL",
                  "HEGART1",
                  "HEGAPP",
                  "HEG360",
                  "HEGPAL"
               ]
            }
         },
         {
            "depart_time": "05:55",
            "travel_time": "1h 25m",
            "stops": "0",
            "flight": "IndiGo",
            "price": 3512,
            "arrival_time": "07:20",
            "coupon": {
               "paytm": [
                  "FLYPTM",
                  "FIRSTFLIGHT",
                  "FIRSTINTLTRIP",
                  "FLY2",
                  "FLY3",
                  "FLY4"
               ],
               "mmt": [
                  "MMTFLIGHT",
                  "MMTNEWFLY",
                  "FLYNOW",
                  "MMTFYLMON",
                  "HSBCDOM",
                  "FLYMON",
                  "RBLMMT",
                  "MMTIDFC"
               ],
               "goibigo": [
                  "FLYNEW",
                  "FLYINT",
                  "WINTER",
                  "MYSTERYDEAL",
                  "GOPAYPAL"
               ],
               "yatra": [
                  "FLASH2020",
                  "FREEFLY",
                  "YTINTFLY",
                  "YATRANEW",
                  "STCEMI",
                  "AXISEMI19",
                  "NEWPAY",
                  "DIGISMART"
               ],
               "happyeasygo": [
                  "HEGNEW",
                  "HEGOLAN",
                  "HEGOLAA",
                  "HEGDMF",
                  "HEGINF",
                  "HEGARTL",
                  "HEGART1",
                  "HEGAPP",
                  "HEG360",
                  "HEGPAL"
               ]
            }
         },
         {
            "depart_time": "15:10",
            "travel_time": "1h 15m",
            "stops": "0",
            "flight": "IndiGo",
            "price": 10432,
            "arrival_time": "16:25",
            "coupon": {
               "paytm": [
                  "FLYPTM",
                  "FIRSTFLIGHT",
                  "FIRSTINTLTRIP",
                  "FLY2",
                  "FLY3",
                  "FLY4"
               ],
               "mmt": [
                  "MMTFLIGHT",
                  "MMTNEWFLY",
                  "FLYNOW",
                  "MMTFYLMON",
                  "HSBCDOM",
                  "FLYMON",
                  "RBLMMT",
                  "MMTIDFC"
               ],
               "goibigo": [
                  "FLYNEW",
                  "FLYINT",
                  "WINTER",
                  "MYSTERYDEAL",
                  "GOPAYPAL"
               ],
               "yatra": [
                  "FLASH2020",
                  "FREEFLY",
                  "YTINTFLY",
                  "YATRANEW",
                  "STCEMI",
                  "AXISEMI19",
                  "NEWPAY",
                  "DIGISMART"
               ],
               "happyeasygo": [
                  "HEGNEW",
                  "HEGOLAN",
                  "HEGOLAA",
                  "HEGDMF",
                  "HEGINF",
                  "HEGARTL",
                  "HEGART1",
                  "HEGAPP",
                  "HEG360",
                  "HEGPAL"
               ]
            }
         },
         {
            "depart_time": "18:25",
            "travel_time": "1h 20m",
            "stops": "0",
            "flight": "IndiGo",
            "price": 8132,
            "arrival_time": "19:45",
            "coupon": {
               "paytm": [
                  "FLYPTM",
                  "FIRSTFLIGHT",
                  "FIRSTINTLTRIP",
                  "FLY2",
                  "FLY3",
                  "FLY4"
               ],
               "mmt": [
                  "MMTFLIGHT",
                  "MMTNEWFLY",
                  "FLYNOW",
                  "MMTFYLMON",
                  "HSBCDOM",
                  "FLYMON",
                  "RBLMMT",
                  "MMTIDFC"
               ],
               "goibigo": [
                  "FLYNEW",
                  "FLYINT",
                  "WINTER",
                  "MYSTERYDEAL",
                  "GOPAYPAL"
               ],
               "yatra": [
                  "FLASH2020",
                  "FREEFLY",
                  "YTINTFLY",
                  "YATRANEW",
                  "STCEMI",
                  "AXISEMI19",
                  "NEWPAY",
                  "DIGISMART"
               ],
               "happyeasygo": [
                  "HEGNEW",
                  "HEGOLAN",
                  "HEGOLAA",
                  "HEGDMF",
                  "HEGINF",
                  "HEGARTL",
                  "HEGART1",
                  "HEGAPP",
                  "HEG360",
                  "HEGPAL"
               ]
            }
         },
         {
            "depart_time": "19:25",
            "travel_time": "1h 20m",
            "stops": "0",
            "flight": "IndiGo",
            "price": 8132,
            "arrival_time": "20:45",
            "coupon": {
               "paytm": [
                  "FLYPTM",
                  "FIRSTFLIGHT",
                  "FIRSTINTLTRIP",
                  "FLY2",
                  "FLY3",
                  "FLY4"
               ],
               "mmt": [
                  "MMTFLIGHT",
                  "MMTNEWFLY",
                  "FLYNOW",
                  "MMTFYLMON",
                  "HSBCDOM",
                  "FLYMON",
                  "RBLMMT",
                  "MMTIDFC"
               ],
               "goibigo": [
                  "FLYNEW",
                  "FLYINT",
                  "WINTER",
                  "MYSTERYDEAL",
                  "GOPAYPAL"
               ],
               "yatra": [
                  "FLASH2020",
                  "FREEFLY",
                  "YTINTFLY",
                  "YATRANEW",
                  "STCEMI",
                  "AXISEMI19",
                  "NEWPAY",
                  "DIGISMART"
               ],
               "happyeasygo": [
                  "HEGNEW",
                  "HEGOLAN",
                  "HEGOLAA",
                  "HEGDMF",
                  "HEGINF",
                  "HEGARTL",
                  "HEGART1",
                  "HEGAPP",
                  "HEG360",
                  "HEGPAL"
               ]
            }
         },
         {
            "depart_time": "21:35",
            "travel_time": "1h 15m",
            "stops": "0",
            "flight": "IndiGo",
            "price": 7450,
            "arrival_time": "22:50",
            "coupon": {
               "paytm": [
                  "FLYPTM",
                  "FIRSTFLIGHT",
                  "FIRSTINTLTRIP",
                  "FLY2",
                  "FLY3",
                  "FLY4"
               ],
               "mmt": [
                  "MMTFLIGHT",
                  "MMTNEWFLY",
                  "FLYNOW",
                  "MMTFYLMON",
                  "HSBCDOM",
                  "FLYMON",
                  "RBLMMT",
                  "MMTIDFC"
               ],
               "goibigo": [
                  "FLYNEW",
                  "FLYINT",
                  "WINTER",
                  "MYSTERYDEAL",
                  "GOPAYPAL"
               ],
               "yatra": [
                  "FLASH2020",
                  "FREEFLY",
                  "YTINTFLY",
                  "YATRANEW",
                  "STCEMI",
                  "AXISEMI19",
                  "NEWPAY",
                  "DIGISMART"
               ],
               "happyeasygo": [
                  "HEGNEW",
                  "HEGOLAN",
                  "HEGOLAA",
                  "HEGDMF",
                  "HEGINF",
                  "HEGARTL",
                  "HEGART1",
                  "HEGAPP",
                  "HEG360",
                  "HEGPAL"
               ]
            }
         },
         {
            "depart_time": "22:10",
            "travel_time": "1h 15m",
            "stops": "0",
            "flight": "IndiGo",
            "price": 7450,
            "arrival_time": "23:25",
            "coupon": {
               "paytm": [
                  "FLYPTM",
                  "FIRSTFLIGHT",
                  "FIRSTINTLTRIP",
                  "FLY2",
                  "FLY3",
                  "FLY4"
               ],
               "mmt": [
                  "MMTFLIGHT",
                  "MMTNEWFLY",
                  "FLYNOW",
                  "MMTFYLMON",
                  "HSBCDOM",
                  "FLYMON",
                  "RBLMMT",
                  "MMTIDFC"
               ],
               "goibigo": [
                  "FLYNEW",
                  "FLYINT",
                  "WINTER",
                  "MYSTERYDEAL",
                  "GOPAYPAL"
               ],
               "yatra": [
                  "FLASH2020",
                  "FREEFLY",
                  "YTINTFLY",
                  "YATRANEW",
                  "STCEMI",
                  "AXISEMI19",
                  "NEWPAY",
                  "DIGISMART"
               ],
               "happyeasygo": [
                  "HEGNEW",
                  "HEGOLAN",
                  "HEGOLAA",
                  "HEGDMF",
                  "HEGINF",
                  "HEGARTL",
                  "HEGART1",
                  "HEGAPP",
                  "HEG360",
                  "HEGPAL"
               ]
            }
         },
         {
            "depart_time": "16:30",
            "travel_time": "4h 15m",
            "stops": "1",
            "flight": "IndiGo",
            "price": 11137,
            "arrival_time": "17:50",
            "coupon": {
               "paytm": [
                  "FLYPTM",
                  "FIRSTFLIGHT",
                  "FIRSTINTLTRIP",
                  "FLY2",
                  "FLY3",
                  "FLY4"
               ],
               "mmt": [
                  "MMTFLIGHT",
                  "MMTNEWFLY",
                  "FLYNOW",
                  "MMTFYLMON",
                  "HSBCDOM",
                  "FLYMON",
                  "RBLMMT",
                  "MMTIDFC"
               ],
               "goibigo": [
                  "FLYNEW",
                  "FLYINT",
                  "WINTER",
                  "MYSTERYDEAL",
                  "GOPAYPAL"
               ],
               "yatra": [
                  "FLASH2020",
                  "FREEFLY",
                  "YTINTFLY",
                  "YATRANEW",
                  "STCEMI",
                  "AXISEMI19",
                  "NEWPAY",
                  "DIGISMART"
               ],
               "happyeasygo": [
                  "HEGNEW",
                  "HEGOLAN",
                  "HEGOLAA",
                  "HEGDMF",
                  "HEGINF",
                  "HEGARTL",
                  "HEGART1",
                  "HEGAPP",
                  "HEG360",
                  "HEGPAL"
               ]
            }
         },
         {
            "depart_time": "06:40",
            "travel_time": "1h 15m",
            "stops": "0",
            "flight": "GoAir",
            "price": 3722,
            "arrival_time": "07:55",
            "coupon": {
               "paytm": [
                  "FLYPTM",
                  "FIRSTFLIGHT",
                  "FIRSTINTLTRIP",
                  "FLY2",
                  "FLY3",
                  "FLY4"
               ],
               "mmt": [
                  "MMTFLIGHT",
                  "MMTNEWFLY",
                  "FLYNOW",
                  "MMTFYLMON",
                  "HSBCDOM",
                  "FLYMON",
                  "RBLMMT",
                  "MMTIDFC"
               ],
               "goibigo": [
                  "FLYNEW",
                  "FLYINT",
                  "WINTER",
                  "MYSTERYDEAL",
                  "GOPAYPAL"
               ],
               "yatra": [
                  "FLASH2020",
                  "FREEFLY",
                  "YTINTFLY",
                  "YATRANEW",
                  "STCEMI",
                  "AXISEMI19",
                  "NEWPAY",
                  "DIGISMART"
               ],
               "happyeasygo": [
                  "HEGNEW",
                  "HEGOLAN",
                  "HEGOLAA",
                  "HEGDMF",
                  "HEGINF",
                  "HEGARTL",
                  "HEGART1",
                  "HEGAPP",
                  "HEG360",
                  "HEGPAL"
               ]
            }
         },
         {
            "depart_time": "06:45",
            "travel_time": "7h 45m",
            "stops": "1",
            "flight": "GoAir",
            "price": 24337,
            "arrival_time": "09:10",
            "coupon": {
               "paytm": [
                  "FLYPTM",
                  "FIRSTFLIGHT",
                  "FIRSTINTLTRIP",
                  "FLY2",
                  "FLY3",
                  "FLY4"
               ],
               "mmt": [
                  "MMTFLIGHT",
                  "MMTNEWFLY",
                  "FLYNOW",
                  "MMTFYLMON",
                  "HSBCDOM",
                  "FLYMON",
                  "RBLMMT",
                  "MMTIDFC"
               ],
               "goibigo": [
                  "FLYNEW",
                  "FLYINT",
                  "WINTER",
                  "MYSTERYDEAL",
                  "GOPAYPAL"
               ],
               "yatra": [
                  "FLASH2020",
                  "FREEFLY",
                  "YTINTFLY",
                  "YATRANEW",
                  "STCEMI",
                  "AXISEMI19",
                  "NEWPAY",
                  "DIGISMART"
               ],
               "happyeasygo": [
                  "HEGNEW",
                  "HEGOLAN",
                  "HEGOLAA",
                  "HEGDMF",
                  "HEGINF",
                  "HEGARTL",
                  "HEGART1",
                  "HEGAPP",
                  "HEG360",
                  "HEGPAL"
               ]
            }
         },
         {
            "depart_time": "13:35",
            "travel_time": "7h 10m",
            "stops": "1",
            "flight": "GoAir",
            "price": 23139,
            "arrival_time": "15:55",
            "coupon": {
               "paytm": [
                  "FLYPTM",
                  "FIRSTFLIGHT",
                  "FIRSTINTLTRIP",
                  "FLY2",
                  "FLY3",
                  "FLY4"
               ],
               "mmt": [
                  "MMTFLIGHT",
                  "MMTNEWFLY",
                  "FLYNOW",
                  "MMTFYLMON",
                  "HSBCDOM",
                  "FLYMON",
                  "RBLMMT",
                  "MMTIDFC"
               ],
               "goibigo": [
                  "FLYNEW",
                  "FLYINT",
                  "WINTER",
                  "MYSTERYDEAL",
                  "GOPAYPAL"
               ],
               "yatra": [
                  "FLASH2020",
                  "FREEFLY",
                  "YTINTFLY",
                  "YATRANEW",
                  "STCEMI",
                  "AXISEMI19",
                  "NEWPAY",
                  "DIGISMART"
               ],
               "happyeasygo": [
                  "HEGNEW",
                  "HEGOLAN",
                  "HEGOLAA",
                  "HEGDMF",
                  "HEGINF",
                  "HEGARTL",
                  "HEGART1",
                  "HEGAPP",
                  "HEG360",
                  "HEGPAL"
               ]
            }
         },
         {
            "depart_time": "13:35",
            "travel_time": "8h 50m",
            "stops": "1",
            "flight": "GoAir",
            "price": 20937,
            "arrival_time": "15:55",
            "coupon": {
               "paytm": [
                  "FLYPTM",
                  "FIRSTFLIGHT",
                  "FIRSTINTLTRIP",
                  "FLY2",
                  "FLY3",
                  "FLY4"
               ],
               "mmt": [
                  "MMTFLIGHT",
                  "MMTNEWFLY",
                  "FLYNOW",
                  "MMTFYLMON",
                  "HSBCDOM",
                  "FLYMON",
                  "RBLMMT",
                  "MMTIDFC"
               ],
               "goibigo": [
                  "FLYNEW",
                  "FLYINT",
                  "WINTER",
                  "MYSTERYDEAL",
                  "GOPAYPAL"
               ],
               "yatra": [
                  "FLASH2020",
                  "FREEFLY",
                  "YTINTFLY",
                  "YATRANEW",
                  "STCEMI",
                  "AXISEMI19",
                  "NEWPAY",
                  "DIGISMART"
               ],
               "happyeasygo": [
                  "HEGNEW",
                  "HEGOLAN",
                  "HEGOLAA",
                  "HEGDMF",
                  "HEGINF",
                  "HEGARTL",
                  "HEGART1",
                  "HEGAPP",
                  "HEG360",
                  "HEGPAL"
               ]
            }
         },
         {
            "depart_time": "13:35",
            "travel_time": "9h 55m",
            "stops": "1",
            "flight": "GoAir",
            "price": 20437,
            "arrival_time": "15:55",
            "coupon": {
               "paytm": [
                  "FLYPTM",
                  "FIRSTFLIGHT",
                  "FIRSTINTLTRIP",
                  "FLY2",
                  "FLY3",
                  "FLY4"
               ],
               "mmt": [
                  "MMTFLIGHT",
                  "MMTNEWFLY",
                  "FLYNOW",
                  "MMTFYLMON",
                  "HSBCDOM",
                  "FLYMON",
                  "RBLMMT",
                  "MMTIDFC"
               ],
               "goibigo": [
                  "FLYNEW",
                  "FLYINT",
                  "WINTER",
                  "MYSTERYDEAL",
                  "GOPAYPAL"
               ],
               "yatra": [
                  "FLASH2020",
                  "FREEFLY",
                  "YTINTFLY",
                  "YATRANEW",
                  "STCEMI",
                  "AXISEMI19",
                  "NEWPAY",
                  "DIGISMART"
               ],
               "happyeasygo": [
                  "HEGNEW",
                  "HEGOLAN",
                  "HEGOLAA",
                  "HEGDMF",
                  "HEGINF",
                  "HEGARTL",
                  "HEGART1",
                  "HEGAPP",
                  "HEG360",
                  "HEGPAL"
               ]
            }
         }
      ]
   }
}
